CODE_STRUCTURE.rst
MANIFEST.in
README.rst
development.txt
requirements.txt
setup.cfg
setup.py
gabrielfalcao_httpbin/__init__.py
gabrielfalcao_httpbin/client.py
gabrielfalcao_httpbin/console.py
gabrielfalcao_httpbin/version.py
gabrielfalcao_httpbin.egg-info/PKG-INFO
gabrielfalcao_httpbin.egg-info/SOURCES.txt
gabrielfalcao_httpbin.egg-info/dependency_links.txt
gabrielfalcao_httpbin.egg-info/entry_points.txt
gabrielfalcao_httpbin.egg-info/not-zip-safe
gabrielfalcao_httpbin.egg-info/requires.txt
gabrielfalcao_httpbin.egg-info/top_level.txt